{
  "schema": "cta-compact-v1",
  "quality_batch": "014",
  "rows": [
    {
      "id": "q014_roof_tile",
      "t": "material",
      "ja": "瓦",
      "en": "Roof Tile",
      "dj": "屋根を覆う焼き物やセメント系の屋根材。",
      "de": "Tile roofing material used to cover pitched roofs.",
      "c": "roof",
      "task": "install_roofing"
    },
    {
      "id": "q014_galvalume_roof",
      "t": "material",
      "ja": "ガルバリウム鋼板屋根",
      "en": "Galvalume Steel Roofing",
      "dj": "アルミ亜鉛めっき鋼板を使う金属屋根。",
      "de": "Metal roofing made from aluminum-zinc coated steel sheet.",
      "c": "roof",
      "task": "install_roofing"
    },
    {
      "id": "q014_standing_seam_roof",
      "t": "material",
      "ja": "立平葺き",
      "en": "Standing Seam Roof",
      "dj": "縦方向のはぜで接合する金属屋根工法。",
      "de": "Metal roofing system joined by raised vertical seams.",
      "c": "roof",
      "task": "install_metal_roof"
    },
    {
      "id": "q014_corrugated_roof_sheet",
      "t": "material",
      "ja": "波板屋根材",
      "en": "Corrugated Roof Sheet",
      "dj": "波形断面の軽量屋根・外装材。",
      "de": "Corrugated sheet used for lightweight roofing or cladding.",
      "c": "roof",
      "task": "install_roof_sheet"
    },
    {
      "id": "q014_roof_batten",
      "t": "component",
      "ja": "瓦桟",
      "en": "Roof Batten",
      "dj": "瓦や屋根材を引っ掛けて固定する横桟。",
      "de": "Horizontal batten used to support roof tiles or panels.",
      "c": "roof",
      "task": "install_roof_base"
    },
    {
      "id": "q014_eave_flashing",
      "t": "component",
      "ja": "軒先水切り",
      "en": "Eave Flashing",
      "dj": "軒先で雨水を外へ逃がす金属部材。",
      "de": "Flashing at the eave that directs rainwater outward.",
      "c": "roof",
      "task": "install_flashing"
    },
    {
      "id": "q014_valley_flashing",
      "t": "component",
      "ja": "谷樋",
      "en": "Valley Flashing",
      "dj": "屋根の谷部で雨水を集めて流す部材。",
      "de": "Flashing that drains water along a roof valley.",
      "c": "roof",
      "task": "drain_roof"
    },
    {
      "id": "q014_drip_edge",
      "t": "component",
      "ja": "ドリップエッジ",
      "en": "Drip Edge",
      "dj": "水切れを良くして水の回り込みを防ぐ端部材。",
      "de": "Edge flashing that improves water drip and prevents backflow.",
      "c": "roof",
      "task": "protect_edge"
    },
    {
      "id": "q014_snow_guard",
      "t": "component",
      "ja": "雪止め金具",
      "en": "Snow Guard",
      "dj": "屋根からの落雪を抑える金具。",
      "de": "Roof hardware that reduces sudden snow sliding.",
      "c": "roof",
      "task": "snow_protection"
    },
    {
      "id": "q014_roof_vent",
      "t": "component",
      "ja": "棟換気",
      "en": "Ridge Vent",
      "dj": "屋根裏の湿気や熱を棟から排出する換気部材。",
      "de": "Vent installed at the ridge to exhaust attic heat or moisture.",
      "c": "roof",
      "task": "vent_roof"
    },
    {
      "id": "q014_roof_sealant",
      "t": "material",
      "ja": "屋根用シーリング材",
      "en": "Roof Sealant",
      "dj": "屋根の取り合いやビス周りを止水する材料。",
      "de": "Sealant used around roof joints and fasteners.",
      "c": "roof",
      "task": "seal_roof"
    },
    {
      "id": "q014_roof_screw",
      "t": "fastener",
      "ja": "屋根ビス",
      "en": "Roofing Screw",
      "dj": "金属屋根や外装材を固定する防水座金付きビス。",
      "de": "Screw with sealing washer used for roofing sheets.",
      "c": "roof",
      "task": "fasten_roof"
    },
    {
      "id": "q014_roofing_nail",
      "t": "fastener",
      "ja": "屋根釘",
      "en": "Roofing Nail",
      "dj": "屋根材や下葺き材を固定する釘。",
      "de": "Nail used to fasten roof materials or underlayment.",
      "c": "roof",
      "task": "fasten_roof"
    },
    {
      "id": "q014_bitumen_primer",
      "t": "material",
      "ja": "アスファルトプライマー",
      "en": "Bitumen Primer",
      "dj": "アスファルト防水材の密着を高める下塗り材。",
      "de": "Primer used to improve adhesion of bituminous waterproofing.",
      "c": "waterproofing",
      "task": "prime_substrate"
    },
    {
      "id": "q014_urethane_waterproofing",
      "t": "material",
      "ja": "ウレタン防水",
      "en": "Urethane Waterproofing",
      "dj": "液状ウレタンを塗って作る塗膜防水。",
      "de": "Liquid-applied urethane membrane waterproofing.",
      "c": "waterproofing",
      "task": "apply_membrane"
    },
    {
      "id": "q014_frp_waterproofing",
      "t": "material",
      "ja": "FRP防水",
      "en": "FRP Waterproofing",
      "dj": "樹脂とガラス繊維で作る硬質な防水層。",
      "de": "Rigid waterproofing system made with resin and glass fiber.",
      "c": "waterproofing",
      "task": "apply_membrane"
    },
    {
      "id": "q014_sheet_membrane",
      "t": "material",
      "ja": "シート防水",
      "en": "Sheet Membrane Waterproofing",
      "dj": "防水シートを貼って作る防水工法。",
      "de": "Waterproofing made by laying membrane sheets.",
      "c": "waterproofing",
      "task": "install_membrane"
    },
    {
      "id": "q014_torch_on_membrane",
      "t": "material",
      "ja": "トーチ工法防水",
      "en": "Torch-On Membrane",
      "dj": "バーナーで加熱して貼り付ける防水シート工法。",
      "de": "Waterproofing membrane applied with torch heat.",
      "c": "waterproofing",
      "task": "install_membrane"
    },
    {
      "id": "q014_waterproof_topcoat",
      "t": "material",
      "ja": "防水トップコート",
      "en": "Waterproofing Topcoat",
      "dj": "防水層を紫外線や摩耗から守る仕上げ塗膜。",
      "de": "Protective coating applied over waterproofing membranes.",
      "c": "waterproofing",
      "task": "protect_membrane"
    },
    {
      "id": "q014_drain_strainer",
      "t": "component",
      "ja": "ドレンストレーナー",
      "en": "Drain Strainer",
      "dj": "屋上ドレンにごみが入るのを防ぐ部材。",
      "de": "Screen used to keep debris out of roof drains.",
      "c": "waterproofing",
      "task": "protect_drain"
    },
    {
      "id": "q014_roof_drain",
      "t": "component",
      "ja": "ルーフドレン",
      "en": "Roof Drain",
      "dj": "屋上やバルコニーの雨水を排水する部材。",
      "de": "Drain fitting used to discharge water from roofs or balconies.",
      "c": "waterproofing",
      "task": "drain_roof"
    },
    {
      "id": "q014_overflow_drain",
      "t": "component",
      "ja": "オーバーフロードレン",
      "en": "Overflow Drain",
      "dj": "排水不良時に水位上昇を逃がす予備排水口。",
      "de": "Secondary drain used when primary drainage is blocked.",
      "c": "waterproofing",
      "task": "drain_overflow"
    },
    {
      "id": "q014_parapet_cap",
      "t": "component",
      "ja": "笠木",
      "en": "Parapet Cap",
      "dj": "パラペットや手すり壁の上端を保護する部材。",
      "de": "Cap installed on parapet tops to protect the edge.",
      "c": "exterior",
      "task": "cap_parapet"
    },
    {
      "id": "q014_coping_joint",
      "t": "component",
      "ja": "笠木ジョイント",
      "en": "Coping Joint",
      "dj": "笠木同士の接続部。止水と伸縮処理が必要。",
      "de": "Joint between coping caps requiring sealing and movement allowance.",
      "c": "exterior",
      "task": "seal_joint"
    },
    {
      "id": "q014_exterior_siding",
      "t": "material",
      "ja": "外壁サイディング",
      "en": "Exterior Siding",
      "dj": "外壁に張る板状の仕上げ材。",
      "de": "Panel cladding used as exterior wall finish.",
      "c": "exterior",
      "task": "install_siding"
    },
    {
      "id": "q014_fiber_cement_siding",
      "t": "material",
      "ja": "窯業系サイディング",
      "en": "Fiber Cement Siding",
      "dj": "セメント質と繊維を主材とする外壁板。",
      "de": "Exterior board made from cementitious and fiber materials.",
      "c": "exterior",
      "task": "install_siding"
    },
    {
      "id": "q014_metal_siding",
      "t": "material",
      "ja": "金属サイディング",
      "en": "Metal Siding",
      "dj": "断熱材付き鋼板などの外壁パネル。",
      "de": "Metal wall siding panel, often with insulation backing.",
      "c": "exterior",
      "task": "install_siding"
    },
    {
      "id": "q014_siding_starter",
      "t": "component",
      "ja": "スターター金物",
      "en": "Siding Starter Strip",
      "dj": "サイディングの最下段を受ける開始部材。",
      "de": "Starter strip used to support the first siding course.",
      "c": "exterior",
      "task": "install_siding"
    },
    {
      "id": "q014_siding_clip",
      "t": "fastener",
      "ja": "サイディング金具",
      "en": "Siding Clip",
      "dj": "サイディングを下地へ留める専用金物。",
      "de": "Clip used to fasten siding panels to the substrate.",
      "c": "exterior",
      "task": "fasten_siding"
    },
    {
      "id": "q014_siding_joint",
      "t": "component",
      "ja": "サイディング目地",
      "en": "Siding Joint",
      "dj": "サイディング板同士の継ぎ目。防水処理が必要。",
      "de": "Joint between siding panels that requires weather sealing.",
      "c": "exterior",
      "task": "seal_siding"
    },
    {
      "id": "q014_vented_rainscreen",
      "t": "system",
      "ja": "通気胴縁",
      "en": "Vented Rainscreen Batten",
      "dj": "外壁裏に通気層を作る下地材。",
      "de": "Batten used to create a ventilated cavity behind cladding.",
      "c": "exterior",
      "task": "vent_wall"
    },
    {
      "id": "q014_weather_barrier",
      "t": "material",
      "ja": "透湿防水シート",
      "en": "Weather-Resistive Barrier",
      "dj": "外壁下地に張る防水・透湿シート。",
      "de": "Membrane that resists water while allowing vapor diffusion.",
      "c": "exterior",
      "task": "install_weather_barrier"
    },
    {
      "id": "q014_housewrap_tape",
      "t": "material",
      "ja": "防水気密テープ",
      "en": "Housewrap Tape",
      "dj": "透湿防水シートの重ねや開口部を処理するテープ。",
      "de": "Tape used to seal laps and openings in housewrap.",
      "c": "exterior",
      "task": "seal_weather_barrier"
    },
    {
      "id": "q014_exterior_corner_trim",
      "t": "component",
      "ja": "外壁コーナー材",
      "en": "Exterior Corner Trim",
      "dj": "外壁の出隅・入隅を仕上げる部材。",
      "de": "Trim used to finish outside or inside wall corners.",
      "c": "exterior",
      "task": "finish_corner"
    },
    {
      "id": "q014_fascia_board",
      "t": "component",
      "ja": "破風板",
      "en": "Fascia Board",
      "dj": "屋根端部に取り付ける横板状部材。",
      "de": "Board installed along roof edges.",
      "c": "exterior",
      "task": "finish_eave"
    },
    {
      "id": "q014_soffit_board",
      "t": "component",
      "ja": "軒天材",
      "en": "Soffit Board",
      "dj": "軒裏を仕上げる板材。",
      "de": "Board used to finish the underside of eaves.",
      "c": "exterior",
      "task": "finish_eave"
    },
    {
      "id": "q014_soffit_vent",
      "t": "component",
      "ja": "軒天換気口",
      "en": "Soffit Vent",
      "dj": "軒天から小屋裏へ空気を入れる換気部材。",
      "de": "Vent installed in soffits to admit attic air.",
      "c": "exterior",
      "task": "vent_eave"
    },
    {
      "id": "q014_window_sash",
      "t": "component",
      "ja": "サッシ",
      "en": "Window Sash",
      "dj": "ガラスを納める窓の枠・可動部材。",
      "de": "Window frame or operable unit that holds glazing.",
      "c": "opening",
      "task": "install_window"
    },
    {
      "id": "q014_aluminum_sash",
      "t": "component",
      "ja": "アルミサッシ",
      "en": "Aluminum Sash",
      "dj": "アルミ製の窓枠・建具。",
      "de": "Aluminum window sash or frame.",
      "c": "opening",
      "task": "install_window"
    },
    {
      "id": "q014_resin_sash",
      "t": "component",
      "ja": "樹脂サッシ",
      "en": "Vinyl Window Frame",
      "dj": "断熱性の高い樹脂製サッシ。",
      "de": "Vinyl window frame with higher thermal performance.",
      "c": "opening",
      "task": "install_window"
    },
    {
      "id": "q014_double_glazing",
      "t": "component",
      "ja": "複層ガラス",
      "en": "Insulated Glass Unit",
      "dj": "二枚以上のガラスで断熱層を持つガラス。",
      "de": "Glazing unit with multiple panes and insulating space.",
      "c": "opening",
      "task": "install_glazing"
    },
    {
      "id": "q014_low_e_glass",
      "t": "component",
      "ja": "Low-Eガラス",
      "en": "Low-E Glass",
      "dj": "熱の出入りを抑える低放射膜付きガラス。",
      "de": "Glass with low-emissivity coating to reduce heat transfer.",
      "c": "opening",
      "task": "install_glazing"
    },
    {
      "id": "q014_window_flashing_tape",
      "t": "material",
      "ja": "開口部防水テープ",
      "en": "Window Flashing Tape",
      "dj": "窓まわりの防水処理に使う粘着テープ。",
      "de": "Tape used to waterproof around window openings.",
      "c": "opening",
      "task": "seal_window"
    },
    {
      "id": "q014_sill_pan",
      "t": "component",
      "ja": "水返し皿板",
      "en": "Sill Pan",
      "dj": "窓下端から侵入した水を外へ逃がす部材。",
      "de": "Flashing pan that drains water at the window sill.",
      "c": "opening",
      "task": "drain_window"
    },
    {
      "id": "q014_door_leaf",
      "t": "component",
      "ja": "ドア本体",
      "en": "Door Leaf",
      "dj": "開閉する板状の建具本体。",
      "de": "The movable panel of a door assembly.",
      "c": "opening",
      "task": "install_door"
    },
    {
      "id": "q014_door_hinge",
      "t": "hardware",
      "ja": "丁番",
      "en": "Door Hinge",
      "dj": "ドアを回転支持する金物。",
      "de": "Hardware that allows a door to swing.",
      "c": "hardware",
      "task": "hang_door"
    },
    {
      "id": "q014_door_closer",
      "t": "hardware",
      "ja": "ドアクローザー",
      "en": "Door Closer",
      "dj": "ドアを自動で閉じる装置。",
      "de": "Device that automatically closes a door.",
      "c": "hardware",
      "task": "install_door_hardware"
    },
    {
      "id": "q014_door_stop",
      "t": "hardware",
      "ja": "戸当たり",
      "en": "Door Stop",
      "dj": "扉の開きすぎや壁への衝突を防ぐ金物。",
      "de": "Hardware that stops a door from over-opening.",
      "c": "hardware",
      "task": "install_door_hardware"
    },
    {
      "id": "q014_door_lockset",
      "t": "hardware",
      "ja": "錠前",
      "en": "Lockset",
      "dj": "扉を施錠・解錠する金物一式。",
      "de": "Door hardware set used for locking and latching.",
      "c": "hardware",
      "task": "install_lock"
    },
    {
      "id": "q014_cylinder_lock",
      "t": "hardware",
      "ja": "シリンダー錠",
      "en": "Cylinder Lock",
      "dj": "鍵で回す円筒形の施錠部品。",
      "de": "Key-operated cylindrical lock component.",
      "c": "hardware",
      "task": "install_lock"
    },
    {
      "id": "q014_door_handle",
      "t": "hardware",
      "ja": "ドアハンドル",
      "en": "Door Handle",
      "dj": "扉を開閉するための取っ手。",
      "de": "Handle used to operate a door.",
      "c": "hardware",
      "task": "install_handle"
    },
    {
      "id": "q014_push_plate",
      "t": "hardware",
      "ja": "押板",
      "en": "Push Plate",
      "dj": "扉を押して開けるための保護板。",
      "de": "Plate used to push a door open and protect its surface.",
      "c": "hardware",
      "task": "install_door_hardware"
    },
    {
      "id": "q014_pull_handle",
      "t": "hardware",
      "ja": "引手",
      "en": "Pull Handle",
      "dj": "扉や引戸を引くための金物。",
      "de": "Handle used to pull a door or sliding panel.",
      "c": "hardware",
      "task": "install_handle"
    },
    {
      "id": "q014_sliding_door_rail",
      "t": "hardware",
      "ja": "引戸レール",
      "en": "Sliding Door Rail",
      "dj": "引戸を走らせるためのレール。",
      "de": "Rail that guides a sliding door.",
      "c": "hardware",
      "task": "install_sliding_door"
    },
    {
      "id": "q014_door_roller",
      "t": "hardware",
      "ja": "戸車",
      "en": "Door Roller",
      "dj": "引戸を滑らかに動かす車輪部品。",
      "de": "Roller used to move a sliding door smoothly.",
      "c": "hardware",
      "task": "install_sliding_door"
    },
    {
      "id": "q014_threshold",
      "t": "component",
      "ja": "沓摺",
      "en": "Threshold",
      "dj": "出入口下部の段差・見切り部材。",
      "de": "Bottom member at a doorway opening.",
      "c": "opening",
      "task": "finish_doorway"
    },
    {
      "id": "q014_glazing_gasket",
      "t": "material",
      "ja": "グレージングガスケット",
      "en": "Glazing Gasket",
      "dj": "ガラスと枠の隙間を保持・止水するゴム材。",
      "de": "Rubber gasket used between glass and frame.",
      "c": "opening",
      "task": "install_glazing"
    },
    {
      "id": "q014_glazing_bead",
      "t": "component",
      "ja": "押縁",
      "en": "Glazing Bead",
      "dj": "ガラスを枠に押さえる細長い部材。",
      "de": "Strip that holds glazing in a frame.",
      "c": "opening",
      "task": "secure_glass"
    },
    {
      "id": "q014_expansion_foam",
      "t": "material",
      "ja": "発泡ウレタンフォーム",
      "en": "Expanding Foam",
      "dj": "隙間充填や断熱補助に使う発泡材。",
      "de": "Expanding foam used to fill gaps or improve insulation.",
      "c": "opening",
      "task": "fill_gap"
    },
    {
      "id": "q014_exterior_paint",
      "t": "material",
      "ja": "外壁塗料",
      "en": "Exterior Paint",
      "dj": "外壁を保護し仕上げる屋外用塗料。",
      "de": "Paint used to protect and finish exterior walls.",
      "c": "paint",
      "task": "paint_exterior"
    },
    {
      "id": "q014_elastomeric_paint",
      "t": "material",
      "ja": "弾性塗料",
      "en": "Elastomeric Paint",
      "dj": "伸縮性を持つ外装用塗膜材。",
      "de": "Flexible coating used on exterior surfaces.",
      "c": "paint",
      "task": "paint_exterior"
    },
    {
      "id": "q014_sealer_coat",
      "t": "material",
      "ja": "シーラー",
      "en": "Sealer Coat",
      "dj": "下地の吸い込みを抑え密着を高める下塗り材。",
      "de": "Base coat used to seal porous substrates and improve adhesion.",
      "c": "paint",
      "task": "prime_surface"
    },
    {
      "id": "q014_filler_coat",
      "t": "material",
      "ja": "フィラー",
      "en": "Filler Coat",
      "dj": "外壁下地の細かな凹凸を埋める下塗り材。",
      "de": "Coating used to fill minor surface irregularities.",
      "c": "paint",
      "task": "prepare_surface"
    },
    {
      "id": "q014_spray_gun",
      "t": "tool",
      "ja": "スプレーガン",
      "en": "Spray Gun",
      "dj": "塗料を霧状に吹き付ける工具。",
      "de": "Tool that sprays paint or coating in a fine mist.",
      "c": "paint",
      "task": "spray_paint"
    },
    {
      "id": "q014_airless_sprayer",
      "t": "equipment",
      "ja": "エアレス塗装機",
      "en": "Airless Sprayer",
      "dj": "高圧で塗料を吹き付ける塗装機。",
      "de": "High-pressure sprayer used for coating application.",
      "c": "paint",
      "task": "spray_paint"
    },
    {
      "id": "q014_scaffold_sheet",
      "t": "material",
      "ja": "養生メッシュシート",
      "en": "Scaffold Mesh Sheet",
      "dj": "足場外周に張る飛散防止用シート。",
      "de": "Mesh sheet attached to scaffolding to contain debris or dust.",
      "c": "temporary_work",
      "task": "protect_site"
    },
    {
      "id": "q014_poly_curing_sheet",
      "t": "material",
      "ja": "ポリシート",
      "en": "Poly Sheet",
      "dj": "養生や防湿に使う薄い樹脂シート。",
      "de": "Plastic sheet used for curing, protection, or moisture control.",
      "c": "curing",
      "task": "protect_surface"
    },
    {
      "id": "q014_floor_protection_board",
      "t": "material",
      "ja": "床養生ボード",
      "en": "Floor Protection Board",
      "dj": "仕上げ床を傷や汚れから守る養生板。",
      "de": "Board used to protect finished floors during work.",
      "c": "curing",
      "task": "protect_floor"
    },
    {
      "id": "q014_corner_guard",
      "t": "component",
      "ja": "コーナーガード",
      "en": "Corner Guard",
      "dj": "柱や壁角を衝撃から守る保護材。",
      "de": "Protector installed on wall or column corners.",
      "c": "hardware",
      "task": "protect_corner"
    },
    {
      "id": "q014_handrail",
      "t": "component",
      "ja": "手すり",
      "en": "Handrail",
      "dj": "歩行や昇降を補助する握り部材。",
      "de": "Rail used for support while walking or climbing.",
      "c": "hardware",
      "task": "install_handrail"
    },
    {
      "id": "q014_guard_post",
      "t": "component",
      "ja": "手すり支柱",
      "en": "Guardrail Post",
      "dj": "手すりや柵を支える縦部材。",
      "de": "Vertical post supporting a guardrail or handrail.",
      "c": "hardware",
      "task": "install_guardrail"
    },
    {
      "id": "q014_baluster",
      "t": "component",
      "ja": "縦格子",
      "en": "Baluster",
      "dj": "手すりや柵の間を埋める縦材。",
      "de": "Vertical member between handrail and base.",
      "c": "hardware",
      "task": "install_railing"
    },
    {
      "id": "q014_exterior_fence",
      "t": "component",
      "ja": "フェンス",
      "en": "Fence",
      "dj": "敷地境界や安全区画を示す外構部材。",
      "de": "Exterior barrier used for boundaries or safety zones.",
      "c": "exterior_site",
      "task": "install_fence"
    },
    {
      "id": "q014_fence_post",
      "t": "component",
      "ja": "フェンス支柱",
      "en": "Fence Post",
      "dj": "フェンス本体を支える柱。",
      "de": "Post that supports fence panels.",
      "c": "exterior_site",
      "task": "install_fence"
    },
    {
      "id": "q014_gate",
      "t": "component",
      "ja": "門扉",
      "en": "Gate",
      "dj": "敷地や通路の出入口に設ける開閉扉。",
      "de": "Movable entrance panel for a site or path.",
      "c": "exterior_site",
      "task": "install_gate"
    },
    {
      "id": "q014_gate_hinge",
      "t": "hardware",
      "ja": "門扉丁番",
      "en": "Gate Hinge",
      "dj": "門扉を回転支持する金物。",
      "de": "Hinge used to support and swing a gate.",
      "c": "hardware",
      "task": "install_gate"
    },
    {
      "id": "q014_gate_latch",
      "t": "hardware",
      "ja": "門扉ラッチ",
      "en": "Gate Latch",
      "dj": "門扉を閉じた状態で保持する金物。",
      "de": "Latch used to keep a gate closed.",
      "c": "hardware",
      "task": "install_gate"
    },
    {
      "id": "q014_interlocking_paver",
      "t": "material",
      "ja": "インターロッキングブロック",
      "en": "Interlocking Paver",
      "dj": "舗装面に敷き並べる噛み合わせ式ブロック。",
      "de": "Paving block installed in interlocking patterns.",
      "c": "paving",
      "task": "lay_paver"
    },
    {
      "id": "q014_concrete_paver",
      "t": "material",
      "ja": "平板ブロック",
      "en": "Concrete Paver Slab",
      "dj": "歩道や庭に敷くコンクリート平板。",
      "de": "Concrete slab used for paths and exterior paving.",
      "c": "paving",
      "task": "lay_paver"
    },
    {
      "id": "q014_paving_stone",
      "t": "material",
      "ja": "舗石",
      "en": "Paving Stone",
      "dj": "外構舗装に使う石材。",
      "de": "Stone used for exterior paving.",
      "c": "paving",
      "task": "lay_stone"
    },
    {
      "id": "q014_curb_block",
      "t": "component",
      "ja": "縁石",
      "en": "Curb Block",
      "dj": "車道や歩道の端部を区切るブロック。",
      "de": "Block used to define the edge of pavement or sidewalk.",
      "c": "paving",
      "task": "install_curb"
    },
    {
      "id": "q014_granite_curb",
      "t": "component",
      "ja": "御影石縁石",
      "en": "Granite Curb",
      "dj": "石材でできた耐久性の高い縁石。",
      "de": "Durable curb made from granite.",
      "c": "paving",
      "task": "install_curb"
    },
    {
      "id": "q014_asphalt_mix",
      "t": "material",
      "ja": "アスファルト合材",
      "en": "Asphalt Mix",
      "dj": "道路や駐車場舗装に使うアスファルト材料。",
      "de": "Asphalt material used for roads or parking surfaces.",
      "c": "paving",
      "task": "pave_asphalt"
    },
    {
      "id": "q014_asphalt_tack_coat",
      "t": "material",
      "ja": "タックコート",
      "en": "Tack Coat",
      "dj": "アスファルト層同士の接着を高める乳剤。",
      "de": "Bituminous emulsion used to bond asphalt layers.",
      "c": "paving",
      "task": "bond_asphalt"
    },
    {
      "id": "q014_asphalt_primer",
      "t": "material",
      "ja": "プライムコート",
      "en": "Prime Coat",
      "dj": "路盤と舗装層の接着や防水を助ける乳剤。",
      "de": "Bituminous coat applied to a base before asphalt paving.",
      "c": "paving",
      "task": "prepare_base"
    },
    {
      "id": "q014_vibratory_roller",
      "t": "equipment",
      "ja": "振動ローラー",
      "en": "Vibratory Roller",
      "dj": "舗装や路盤を振動で締め固める機械。",
      "de": "Roller used to compact pavement or base layers by vibration.",
      "c": "paving",
      "task": "compact_pavement"
    },
    {
      "id": "q014_hand_roller",
      "t": "equipment",
      "ja": "ハンドローラー",
      "en": "Walk-Behind Roller",
      "dj": "小規模舗装を締め固める手押しローラー。",
      "de": "Walk-behind roller used for small paving areas.",
      "c": "paving",
      "task": "compact_pavement"
    },
    {
      "id": "q014_asphalt_rake",
      "t": "tool",
      "ja": "アスファルトレーキ",
      "en": "Asphalt Rake",
      "dj": "アスファルト合材をならすレーキ。",
      "de": "Rake used to spread and level asphalt mix.",
      "c": "paving",
      "task": "spread_asphalt"
    },
    {
      "id": "q014_lute_rake",
      "t": "tool",
      "ja": "ルートレーキ",
      "en": "Asphalt Lute",
      "dj": "舗装面を平滑にならす長柄の工具。",
      "de": "Long-handled tool used to smooth asphalt surfaces.",
      "c": "paving",
      "task": "level_asphalt"
    },
    {
      "id": "q014_paver_machine",
      "t": "equipment",
      "ja": "アスファルトフィニッシャー",
      "en": "Asphalt Paver",
      "dj": "アスファルトを敷き均す舗装機械。",
      "de": "Machine used to place and level asphalt pavement.",
      "c": "paving",
      "task": "pave_asphalt"
    },
    {
      "id": "q014_line_marking_paint",
      "t": "material",
      "ja": "路面標示塗料",
      "en": "Line Marking Paint",
      "dj": "駐車場や道路のラインを描く塗料。",
      "de": "Paint used for road or parking lot line marking.",
      "c": "paving",
      "task": "mark_pavement"
    },
    {
      "id": "q014_trench_drain",
      "t": "component",
      "ja": "側溝",
      "en": "Trench Drain",
      "dj": "地表水を線状に集めて流す排水溝。",
      "de": "Linear drain used to collect surface water.",
      "c": "drainage",
      "task": "install_drain"
    },
    {
      "id": "q014_grating",
      "t": "component",
      "ja": "グレーチング",
      "en": "Grating",
      "dj": "側溝や排水桝を覆う格子状の蓋。",
      "de": "Grid cover used over drains or pits.",
      "c": "drainage",
      "task": "cover_drain"
    },
    {
      "id": "q014_drain_channel",
      "t": "component",
      "ja": "排水チャンネル",
      "en": "Drainage Channel",
      "dj": "水を一定方向へ流すU字状の排水部材。",
      "de": "Channel used to convey surface water.",
      "c": "drainage",
      "task": "drain_surface"
    },
    {
      "id": "q014_stormwater_inlet",
      "t": "component",
      "ja": "雨水桝",
      "en": "Stormwater Inlet",
      "dj": "雨水を集めて排水管へ流す桝。",
      "de": "Inlet that collects stormwater into drainage piping.",
      "c": "drainage",
      "task": "collect_water"
    },
    {
      "id": "q014_catchpit",
      "t": "component",
      "ja": "集水ピット",
      "en": "Catch Pit",
      "dj": "排水や土砂を一時的に受ける桝。",
      "de": "Pit used to collect water or sediment.",
      "c": "drainage",
      "task": "collect_water"
    },
    {
      "id": "q014_sediment_trap",
      "t": "component",
      "ja": "泥溜め",
      "en": "Sediment Trap",
      "dj": "土砂を沈めて排水管への流入を抑える部分。",
      "de": "Trap that captures sediment before water enters drainage lines.",
      "c": "drainage",
      "task": "control_sediment"
    },
    {
      "id": "q014_drain_cover",
      "t": "component",
      "ja": "排水蓋",
      "en": "Drain Cover",
      "dj": "排水口を保護する蓋。",
      "de": "Cover installed over a drain opening.",
      "c": "drainage",
      "task": "cover_drain"
    },
    {
      "id": "q014_permeable_paver",
      "t": "material",
      "ja": "透水性舗装材",
      "en": "Permeable Paver",
      "dj": "雨水を地中へ浸透させる舗装材。",
      "de": "Paver that allows water to pass through the surface.",
      "c": "paving",
      "task": "manage_runoff"
    },
    {
      "id": "q014_drainage_slope",
      "t": "process",
      "ja": "排水勾配",
      "en": "Drainage Slope",
      "dj": "水を流すために設ける床や舗装の傾き。",
      "de": "Slope provided to direct water toward drainage.",
      "c": "drainage",
      "task": "set_slope"
    },
    {
      "id": "q014_expansion_joint_filler",
      "t": "material",
      "ja": "目地材フォーム",
      "en": "Expansion Joint Filler",
      "dj": "伸縮目地に入れる圧縮性の充填材。",
      "de": "Compressible filler used in expansion joints.",
      "c": "joint",
      "task": "fill_joint"
    },
    {
      "id": "q014_joint_sealant_exterior",
      "t": "material",
      "ja": "外装目地シーリング",
      "en": "Exterior Joint Sealant",
      "dj": "外壁や建具まわりの目地を防水する材料。",
      "de": "Sealant used for exterior wall or opening joints.",
      "c": "sealant",
      "task": "seal_exterior_joint"
    },
    {
      "id": "q014_polyurethane_sealant",
      "t": "material",
      "ja": "ポリウレタンシーリング",
      "en": "Polyurethane Sealant",
      "dj": "外装目地に使う弾性シーリング材。",
      "de": "Elastic sealant commonly used for exterior joints.",
      "c": "sealant",
      "task": "seal_joint"
    },
    {
      "id": "q014_modified_silicone_sealant",
      "t": "material",
      "ja": "変成シリコーンシーリング",
      "en": "Modified Silicone Sealant",
      "dj": "塗装性や耐候性を持つシーリング材。",
      "de": "Weather-resistant sealant with paintable properties.",
      "c": "sealant",
      "task": "seal_joint"
    },
    {
      "id": "q014_masking_for_sealant",
      "t": "material",
      "ja": "シーリング用マスキング",
      "en": "Sealant Masking Tape",
      "dj": "シーリング目地の端部を整えるためのテープ。",
      "de": "Tape used to keep sealant joint edges clean.",
      "c": "sealant",
      "task": "mask_joint"
    },
    {
      "id": "q014_sealant_spatula",
      "t": "tool",
      "ja": "シーリングヘラ",
      "en": "Sealant Spatula",
      "dj": "シーリング材を押さえ均す工具。",
      "de": "Spatula used to tool and smooth sealant.",
      "c": "sealant",
      "task": "tool_sealant"
    },
    {
      "id": "q014_backer_tape",
      "t": "material",
      "ja": "ボンドブレーカー",
      "en": "Bond Breaker Tape",
      "dj": "三面接着を避けるために目地底へ貼るテープ。",
      "de": "Tape used to prevent three-sided sealant adhesion.",
      "c": "sealant",
      "task": "prepare_joint"
    },
    {
      "id": "q014_glass_suction_cup",
      "t": "tool",
      "ja": "ガラス吸盤",
      "en": "Glass Suction Cup",
      "dj": "ガラスやパネルを持ち運ぶ吸着工具。",
      "de": "Suction tool used to carry glass or panels.",
      "c": "opening",
      "task": "handle_glass"
    },
    {
      "id": "q014_panel_lifter_exterior",
      "t": "equipment",
      "ja": "外装パネルリフター",
      "en": "Panel Lifter",
      "dj": "外壁パネルを持ち上げて位置合わせする機器。",
      "de": "Lifter used to position exterior panels.",
      "c": "exterior",
      "task": "install_panel"
    }
  ]
}
